nordigen_account/__init__.py
nordigen_account-0.3.1.dist-info/LICENSE
nordigen_account-0.3.1.dist-info/METADATA
nordigen_account-0.3.1.dist-info/WHEEL
nordigen_account-0.3.1.dist-info/top_level.txt
nordigen_account-0.3.1.dist-info/RECORD
