Metadata-Version: 2.1
Name: nordigen_account
Version: 0.3.1
Summary: A Python package to interact with Nordigen API for bank account management.
Home-page: https://github.com/rahulpdev/nordigen_account
Author: Rahul Parmar
Author-email: rahulparmaruk@gmail.com
License: MIT
Keywords: nordigen api bank accounts finance
Requires-Python: >=3.7
License-File: LICENSE
Requires-Dist: nordigen>=1.4.1
